LICENSE
MANIFEST.in
README.md
pyproject.toml
requirements.txt
setup.cfg
setup.py
test_requirements.txt
version.txt
cast_ai/__init__.py
cast_ai/se/__init__.py
cast_ai/se/constants.py
cast_ai/se/misc_utils.py
cast_ai/se/contollers/__init__.py
cast_ai/se/contollers/aks_controller.py
cast_ai/se/contollers/castai_controller.py
cast_ai/se/contollers/cloud_controller.py
cast_ai/se/contollers/eks_controller.py
cast_ai/se/contollers/gke_controller.py
cast_ai/se/contollers/kubectl_controller.py
cast_ai/se/contollers/snapshot_controller.py
cast_ai/se/models/__init__.py
cast_ai/se/models/cloud_confs.py
cast_ai/se/models/exceptions.py
cast_ai/se/models/execution_status.py
cast_ai/se/models/misc_data_models.py
cast_ai/se/models/refined_snapshot.py
cast_ai/se/models/refined_snapshot_analysis.py
cast_ai/se/services/__init__.py
cast_ai/se/services/api_requests_svc.py
cast_ai/se/services/request_handle_svc.py
cast_ai/se/services/snapshot_analysis_svc.py
cast_ai/se/services/snapshot_refinery_svc.py
cast_ai/se/services/snapshot_reporting_svc.py
cast_ai_se_tools.egg-info/PKG-INFO
cast_ai_se_tools.egg-info/SOURCES.txt
cast_ai_se_tools.egg-info/dependency_links.txt
cast_ai_se_tools.egg-info/requires.txt
cast_ai_se_tools.egg-info/top_level.txt
tests/__init__.py
tests/test_api_requests_svc.py