Metadata-Version: 2.1
Name: cast_ai-se-tools
Version: 0.0.65
Summary: Provides tools for SE projects (e.g. Cloud controllers).
Author: Dan Amzulescu
Author-email: dan@cast.ai
Keywords: cast.ai k8s eks aks gke
Classifier: Development Status :: 4 - Beta
Classifier: Intended Audience :: Customer Service
Classifier: Topic :: Software Development :: Libraries
Classifier: License :: OSI Approved :: Apache Software License
Classifier: Programming Language :: Python
Requires-Python: >=3.8
License-File: LICENSE
Requires-Dist: python-dotenv==1.0.0
Requires-Dist: requests==2.31.0
Requires-Dist: boto3==1.33.10
Requires-Dist: yaspin==3.0.1
Requires-Dist: azure-identity==1.15.0
Requires-Dist: azure-mgmt-containerservice==28.0.0
Requires-Dist: google-cloud-container==2.36.0
Requires-Dist: google-cloud-storage==2.14.0
Requires-Dist: google-cloud-core==2.4.1
Requires-Dist: pyyaml==6.0.1
Requires-Dist: pandas==2.2.1
Requires-Dist: datetime==5.5
